odoo9_addon_purchase_tier_validation-9.0.1.1.0-py2.7-nspkg.pth
odoo9_addon_purchase_tier_validation-9.0.1.1.0.dist-info/DESCRIPTION.rst
odoo9_addon_purchase_tier_validation-9.0.1.1.0.dist-info/METADATA
odoo9_addon_purchase_tier_validation-9.0.1.1.0.dist-info/RECORD
odoo9_addon_purchase_tier_validation-9.0.1.1.0.dist-info/WHEEL
odoo9_addon_purchase_tier_validation-9.0.1.1.0.dist-info/metadata.json
odoo9_addon_purchase_tier_validation-9.0.1.1.0.dist-info/namespace_packages.txt
odoo9_addon_purchase_tier_validation-9.0.1.1.0.dist-info/top_level.txt
odoo_addons/purchase_tier_validation/README.rst
odoo_addons/purchase_tier_validation/__init__.py
odoo_addons/purchase_tier_validation/__openerp__.py
odoo_addons/purchase_tier_validation/models/__init__.py
odoo_addons/purchase_tier_validation/models/purchase_order.py
odoo_addons/purchase_tier_validation/models/tier_definition.py
odoo_addons/purchase_tier_validation/views/purchase_order_view.xml
